setup.cfg
setup.py
runcurl/__init__.py
runcurl/api.py
runcurl/bin.py
runcurl.egg-info/PKG-INFO
runcurl.egg-info/SOURCES.txt
runcurl.egg-info/dependency_links.txt
runcurl.egg-info/entry_points.txt
runcurl.egg-info/top_level.txt