Metadata-Version: 1.0
Name: runcurl
Version: 0.4
Summary: A fork of uncurl which includes an execute method to run curl directly.
Home-page: https://github.com/halilozercan/runcurl
Author: Steve Pulec, Halil Ozercan
Author-email: halilozercan@gmail
License: UNKNOWN
Platform: UNKNOWN
